quantlab_launcher/__init__.py
quantlab_launcher/_version.py
quantlab_launcher/app.py
quantlab_launcher/error.html
quantlab_launcher/ext_handler.py
quantlab_launcher/ext_manager.py
quantlab_launcher/handlers.py
quantlab_launcher/index.html
quantlab_launcher/settings_handler.py
quantlab_launcher/tests/__init__.py
quantlab_launcher/tests/test_settings_api.py
quantlab_launcher/tests/utils.py
quantlab_launcher-0.3.0.dist-info/DESCRIPTION.rst
quantlab_launcher-0.3.0.dist-info/METADATA
quantlab_launcher-0.3.0.dist-info/RECORD
quantlab_launcher-0.3.0.dist-info/WHEEL
quantlab_launcher-0.3.0.dist-info/metadata.json
quantlab_launcher-0.3.0.dist-info/top_level.txt
