Metadata-Version: 2.0
Name: quantlab-launcher
Version: 0.3.0
Summary: Jupyter Launcher
Home-page: https://www.quantlab.io
Author: QuantLab Development Team
Author-email: quantlab.io@gmail.com
License: BSD
Keywords: Jupyter,QuantLab
Platform: Linux
Platform: Mac OS X
Platform: Windows
Classifier: Intended Audience :: Developers
Classifier: Intended Audience :: System Administrators
Classifier: Intended Audience :: Science/Research
Classifier: License :: OSI Approved :: BSD License
Classifier: Programming Language :: Python
Classifier: Programming Language :: Python :: 2.7
Classifier: Programming Language :: Python :: 3
Classifier: Programming Language :: Python :: 3.4
Classifier: Programming Language :: Python :: 3.5
Requires-Dist: notebook (>=4.2.0)
Provides-Extra: test
Requires-Dist: pytest; extra == 'test'
Requires-Dist: requests; extra == 'test'
Provides-Extra: test
Requires-Dist: mock; python_version == "2.7" and extra == 'test'
